{
"meta":{"test_sets":[],"test_metrics":[],"learn_metrics":[{"best_value":"Min","name":"Logloss"}],"launch_mode":"Train","parameters":"","iteration_count":400,"learn_sets":["learn"],"name":"experiment"},
"iterations":[
{"learn":[0.6845611388],"iteration":0,"passed_time":0.00142508524,"remaining_time":0.5686090106},
{"learn":[0.6759339464],"iteration":1,"passed_time":0.002528364942,"remaining_time":0.5031446235},
{"learn":[0.668429098],"iteration":2,"passed_time":0.003853625471,"remaining_time":0.509963104},
{"learn":[0.6609360681],"iteration":3,"passed_time":0.00514168088,"remaining_time":0.5090264071},
{"learn":[0.6540085352],"iteration":4,"passed_time":0.006394114366,"remaining_time":0.5051350349},
{"learn":[0.647326214],"iteration":5,"passed_time":0.007566471435,"remaining_time":0.4968649576},
{"learn":[0.6407826796],"iteration":6,"passed_time":0.008790157404,"remaining_time":0.4935045514},
{"learn":[0.6362359751],"iteration":7,"passed_time":0.01007362988,"remaining_time":0.4936078639},
{"learn":[0.6315999302],"iteration":8,"passed_time":0.01137130945,"remaining_time":0.4940202218},
{"learn":[0.6269920538],"iteration":9,"passed_time":0.01264182471,"remaining_time":0.4930311637},
{"learn":[0.6235317807],"iteration":10,"passed_time":0.01388942528,"remaining_time":0.4911805849},
{"learn":[0.6191465343],"iteration":11,"passed_time":0.01511061147,"remaining_time":0.4885764374},
{"learn":[0.6165581737],"iteration":12,"passed_time":0.0165241977,"remaining_time":0.4919126546},
{"learn":[0.6144590726],"iteration":13,"passed_time":0.01777000676,"remaining_time":0.489944472},
{"learn":[0.6113310879],"iteration":14,"passed_time":0.0189862767,"remaining_time":0.4873144353},
{"learn":[0.6097865414],"iteration":15,"passed_time":0.02023916848,"remaining_time":0.4857400435},
{"learn":[0.6071974666],"iteration":16,"passed_time":0.02169841743,"remaining_time":0.488852581},
{"learn":[0.6042805469],"iteration":17,"passed_time":0.02280494686,"remaining_time":0.48397165},
{"learn":[0.6017203986],"iteration":18,"passed_time":0.02390826822,"remaining_time":0.4794236944},
{"learn":[0.6000612623],"iteration":19,"passed_time":0.02506979289,"remaining_time":0.476326065},
{"learn":[0.5977209764],"iteration":20,"passed_time":0.02635859824,"remaining_time":0.4757099396},
{"learn":[0.5957212588],"iteration":21,"passed_time":0.02750062459,"remaining_time":0.4725107317},
{"learn":[0.5930464416],"iteration":22,"passed_time":0.02863944289,"remaining_time":0.4694378248},
{"learn":[0.5909283677],"iteration":23,"passed_time":0.03001678226,"remaining_time":0.470262922},
{"learn":[0.588812674],"iteration":24,"passed_time":0.03113410241,"remaining_time":0.4670115362},
{"learn":[0.5867105196],"iteration":25,"passed_time":0.0322062598,"remaining_time":0.4632746603},
{"learn":[0.5846741986],"iteration":26,"passed_time":0.03343019575,"remaining_time":0.4618319635},
{"learn":[0.5830565786],"iteration":27,"passed_time":0.03462205114,"remaining_time":0.4599786794},
{"learn":[0.580596869],"iteration":28,"passed_time":0.03580103263,"remaining_time":0.458006314},
{"learn":[0.580102322],"iteration":29,"passed_time":0.03702588517,"remaining_time":0.4566525838},
{"learn":[0.5795445117],"iteration":30,"passed_time":0.0381667033,"remaining_time":0.4543068876},
{"learn":[0.5789981838],"iteration":31,"passed_time":0.03935026773,"remaining_time":0.4525280789},
{"learn":[0.5782697523],"iteration":32,"passed_time":0.04048167,"remaining_time":0.4502052391},
{"learn":[0.5768224074],"iteration":33,"passed_time":0.04164365297,"remaining_time":0.4482816761},
{"learn":[0.5764274722],"iteration":34,"passed_time":0.04285904799,"remaining_time":0.4469586433},
{"learn":[0.5760045635],"iteration":35,"passed_time":0.043970327,"remaining_time":0.4445888619},
{"learn":[0.5754087216],"iteration":36,"passed_time":0.04539645382,"remaining_time":0.4453760199},
{"learn":[0.5745861516],"iteration":37,"passed_time":0.04667234361,"remaining_time":0.4446154839},
{"learn":[0.5739559793],"iteration":38,"passed_time":0.04804172533,"remaining_time":0.444693919},
{"learn":[0.5730839209],"iteration":39,"passed_time":0.04921987356,"remaining_time":0.4429788621},
{"learn":[0.5727267148],"iteration":40,"passed_time":0.05071245297,"remaining_time":0.4440431858},
{"learn":[0.5721120144],"iteration":41,"passed_time":0.05199488387,"remaining_time":0.4431944863},
{"learn":[0.5711480875],"iteration":42,"passed_time":0.05332489399,"remaining_time":0.4427206315},
{"learn":[0.5704196839],"iteration":43,"passed_time":0.0545592457,"remaining_time":0.441433897},
{"learn":[0.5700111656],"iteration":44,"passed_time":0.05574868463,"remaining_time":0.4397951787},
{"learn":[0.5693830165],"iteration":45,"passed_time":0.05690487643,"remaining_time":0.437920136},
{"learn":[0.568012056],"iteration":46,"passed_time":0.05806702604,"remaining_time":0.4361204296},
{"learn":[0.5674171321],"iteration":47,"passed_time":0.05955377262,"remaining_time":0.4367276659},
{"learn":[0.567114481],"iteration":48,"passed_time":0.06081741347,"remaining_time":0.435651268},
{"learn":[0.5667265925],"iteration":49,"passed_time":0.06200839394,"remaining_time":0.4340587575},
{"learn":[0.5654926367],"iteration":50,"passed_time":0.06318358409,"remaining_time":0.4323739382},
{"learn":[0.5644601103],"iteration":51,"passed_time":0.06458287989,"remaining_time":0.4322085039},
{"learn":[0.5636330128],"iteration":52,"passed_time":0.06576265299,"remaining_time":0.4305592564},
{"learn":[0.5633466174],"iteration":53,"passed_time":0.06709299641,"remaining_time":0.4298921622},
{"learn":[0.5627074948],"iteration":54,"passed_time":0.06836434493,"remaining_time":0.4288308909},
{"learn":[0.5625493425],"iteration":55,"passed_time":0.06966369103,"remaining_time":0.4279341021},
{"learn":[0.5618678343],"iteration":56,"passed_time":0.07096545359,"remaining_time":0.4270377295},
{"learn":[0.5606827784],"iteration":57,"passed_time":0.07238703913,"remaining_time":0.4268339204},
{"learn":[0.5602779328],"iteration":58,"passed_time":0.07369121815,"remaining_time":0.4259102608},
{"learn":[0.5591204449],"iteration":59,"passed_time":0.07517971458,"remaining_time":0.4260183826},
{"learn":[0.558285126],"iteration":60,"passed_time":0.07666812768,"remaining_time":0.4260736932},
{"learn":[0.5574336016],"iteration":61,"passed_time":0.07785448354,"remaining_time":0.424432507},
{"learn":[0.5565283026],"iteration":62,"passed_time":0.07905733798,"remaining_time":0.4228940142},
{"learn":[0.5560231664],"iteration":63,"passed_time":0.08027635768,"remaining_time":0.4214508778},
{"learn":[0.555754252],"iteration":64,"passed_time":0.08170481763,"remaining_time":0.4210940601},
{"learn":[0.5552415488],"iteration":65,"passed_time":0.08287850792,"remaining_time":0.4194154795},
{"learn":[0.5547164493],"iteration":66,"passed_time":0.08405723943,"remaining_time":0.4177770258},
{"learn":[0.5542854748],"iteration":67,"passed_time":0.08528888305,"remaining_time":0.416410429},
{"learn":[0.5535541263],"iteration":68,"passed_time":0.08642270178,"remaining_time":0.414578468},
{"learn":[0.552755814],"iteration":69,"passed_time":0.08753756382,"remaining_time":0.4126770866},
{"learn":[0.552013907],"iteration":70,"passed_time":0.08887648983,"remaining_time":0.4118361289},
{"learn":[0.5512873161],"iteration":71,"passed_time":0.08998639396,"remaining_time":0.4099380169},
{"learn":[0.5509943853],"iteration":72,"passed_time":0.09110442239,"remaining_time":0.4080978921},
{"learn":[0.5505415329],"iteration":73,"passed_time":0.09232769173,"remaining_time":0.4067409122},
{"learn":[0.5499921195],"iteration":74,"passed_time":0.09349992381,"remaining_time":0.4051663365},
{"learn":[0.5495832883],"iteration":75,"passed_time":0.09460420343,"remaining_time":0.4033126567},
{"learn":[0.549229234],"iteration":76,"passed_time":0.09581901516,"remaining_time":0.4019421026},
{"learn":[0.5483541876],"iteration":77,"passed_time":0.09690283821,"remaining_time":0.4000347936},
{"learn":[0.5477644012],"iteration":78,"passed_time":0.09800574295,"remaining_time":0.3982258669},
{"learn":[0.5472484813],"iteration":79,"passed_time":0.09914364466,"remaining_time":0.3965745786},
{"learn":[0.5468885332],"iteration":80,"passed_time":0.1003355834,"remaining_time":0.3951487789},
{"learn":[0.546264526],"iteration":81,"passed_time":0.1015039408,"remaining_time":0.3936372338},
{"learn":[0.545877656],"iteration":82,"passed_time":0.1027232521,"remaining_time":0.3923285654},
{"learn":[0.5456126057],"iteration":83,"passed_time":0.1038269485,"remaining_time":0.3905870918},
{"learn":[0.545097833],"iteration":84,"passed_time":0.1050564256,"remaining_time":0.3893267537},
{"learn":[0.5446820964],"iteration":85,"passed_time":0.1061953272,"remaining_time":0.3877364273},
{"learn":[0.5444184002],"iteration":86,"passed_time":0.1073084811,"remaining_time":0.3860638457},
{"learn":[0.5438853263],"iteration":87,"passed_time":0.1085774548,"remaining_time":0.3849564307},
{"learn":[0.5433926295],"iteration":88,"passed_time":0.1096478623,"remaining_time":0.383151519},
{"learn":[0.5428963062],"iteration":89,"passed_time":0.1108013877,"remaining_time":0.3816492243},
{"learn":[0.5425399904],"iteration":90,"passed_time":0.1118425061,"remaining_time":0.3797729054},
{"learn":[0.5421448046],"iteration":91,"passed_time":0.1129264541,"remaining_time":0.3780581291},
{"learn":[0.5418910638],"iteration":92,"passed_time":0.1142437987,"remaining_time":0.3771273785},
{"learn":[0.5416032355],"iteration":93,"passed_time":0.1153774508,"remaining_time":0.3755904249},
{"learn":[0.5409467002],"iteration":94,"passed_time":0.1165228102,"remaining_time":0.3740995485},
{"learn":[0.5403389997],"iteration":95,"passed_time":0.1176085497,"remaining_time":0.3724270741},
{"learn":[0.540017609],"iteration":96,"passed_time":0.1187524926,"remaining_time":0.3709485078},
{"learn":[0.5397355682],"iteration":97,"passed_time":0.1198579388,"remaining_time":0.3693581378},
{"learn":[0.5393398621],"iteration":98,"passed_time":0.120889933,"remaining_time":0.3675542406},
{"learn":[0.5391059088],"iteration":99,"passed_time":0.1220709143,"remaining_time":0.3662127428},
{"learn":[0.5386819898],"iteration":100,"passed_time":0.1232473543,"remaining_time":0.3648609797},
{"learn":[0.5381042549],"iteration":101,"passed_time":0.1244471257,"remaining_time":0.3635808182},
{"learn":[0.5374234207],"iteration":102,"passed_time":0.1256035675,"remaining_time":0.3621772771},
{"learn":[0.5371569958],"iteration":103,"passed_time":0.1266909319,"remaining_time":0.3605818831},
{"learn":[0.5368362884],"iteration":104,"passed_time":0.1277904619,"remaining_time":0.3590303454},
{"learn":[0.5365708159],"iteration":105,"passed_time":0.1289015326,"remaining_time":0.3575193452},
{"learn":[0.5363393328],"iteration":106,"passed_time":0.1301266351,"remaining_time":0.3563280756},
{"learn":[0.5358925706],"iteration":107,"passed_time":0.1312345811,"remaining_time":0.3548194229},
{"learn":[0.5355532707],"iteration":108,"passed_time":0.132454809,"remaining_time":0.3536178846},
{"learn":[0.5351030885],"iteration":109,"passed_time":0.1336028765,"remaining_time":0.3522257654},
{"learn":[0.5343725901],"iteration":110,"passed_time":0.1347334455,"remaining_time":0.3507924843},
{"learn":[0.5338981681],"iteration":111,"passed_time":0.135847766,"remaining_time":0.3493228267},
{"learn":[0.5334210621],"iteration":112,"passed_time":0.1371138233,"remaining_time":0.3482448432},
{"learn":[0.5330081217],"iteration":113,"passed_time":0.1388465903,"remaining_time":0.3483344282},
{"learn":[0.5325660065],"iteration":114,"passed_time":0.1401296461,"remaining_time":0.3472778186},
{"learn":[0.5323140522],"iteration":115,"passed_time":0.1414941949,"remaining_time":0.346416822},
{"learn":[0.5320545131],"iteration":116,"passed_time":0.1426099319,"remaining_time":0.3449453907},
{"learn":[0.531732773],"iteration":117,"passed_time":0.1438535744,"remaining_time":0.343785661},
{"learn":[0.5312067616],"iteration":118,"passed_time":0.1449361059,"remaining_time":0.3422440821},
{"learn":[0.5309560825],"iteration":119,"passed_time":0.1460637585,"remaining_time":0.3408154366},
{"learn":[0.5306901964],"iteration":120,"passed_time":0.1471568724,"remaining_time":0.3393121274},
{"learn":[0.5302475658],"iteration":121,"passed_time":0.1483140225,"remaining_time":0.3379614611},
{"learn":[0.5297917051],"iteration":122,"passed_time":0.1495195017,"remaining_time":0.3367227803},
{"learn":[0.5294757515],"iteration":123,"passed_time":0.1506621113,"remaining_time":0.3353446994},
{"learn":[0.5291024846],"iteration":124,"passed_time":0.1519990792,"remaining_time":0.3343979742},
{"learn":[0.5289030084],"iteration":125,"passed_time":0.1532810518,"remaining_time":0.3333254618},
{"learn":[0.5285583702],"iteration":126,"passed_time":0.1543307945,"remaining_time":0.3317504479},
{"learn":[0.5283661561],"iteration":127,"passed_time":0.155450781,"remaining_time":0.3303329097},
{"learn":[0.5280389598],"iteration":128,"passed_time":0.1566580934,"remaining_time":0.3291034366},
{"learn":[0.5276889313],"iteration":129,"passed_time":0.1579043191,"remaining_time":0.3279551243},
{"learn":[0.5272667121],"iteration":130,"passed_time":0.15907126,"remaining_time":0.326642511},
{"learn":[0.5268394688],"iteration":131,"passed_time":0.1601539165,"remaining_time":0.3251609819},
{"learn":[0.526594922],"iteration":132,"passed_time":0.1613086917,"remaining_time":0.3238302308},
{"learn":[0.5262546743],"iteration":133,"passed_time":0.1625916642,"remaining_time":0.3227565872},
{"learn":[0.5260907417],"iteration":134,"passed_time":0.1637768952,"remaining_time":0.3214879795},
{"learn":[0.5256524643],"iteration":135,"passed_time":0.165137111,"remaining_time":0.3205602744},
{"learn":[0.5249956253],"iteration":136,"passed_time":0.1665516555,"remaining_time":0.3197305504},
{"learn":[0.5247208709],"iteration":137,"passed_time":0.1677045559,"remaining_time":0.3183956062},
{"learn":[0.5242916564],"iteration":138,"passed_time":0.1688934949,"remaining_time":0.3171309509},
{"learn":[0.5240706809],"iteration":139,"passed_time":0.1701879248,"remaining_time":0.3160632889},
{"learn":[0.523784042],"iteration":140,"passed_time":0.1713066615,"remaining_time":0.3146696831},
{"learn":[0.5233053523],"iteration":141,"passed_time":0.1726395463,"remaining_time":0.3136690349},
{"learn":[0.5230783599],"iteration":142,"passed_time":0.1737583247,"remaining_time":0.3122789472},
{"learn":[0.5228316016],"iteration":143,"passed_time":0.1751248317,"remaining_time":0.3113330341},
{"learn":[0.5226201405],"iteration":144,"passed_time":0.1763966385,"remaining_time":0.310214778},
{"learn":[0.5223153003],"iteration":145,"passed_time":0.1774988349,"remaining_time":0.308799343},
{"learn":[0.5220371779],"iteration":146,"passed_time":0.1786466525,"remaining_time":0.3074666876},
{"learn":[0.5215937667],"iteration":147,"passed_time":0.1796955202,"remaining_time":0.3059680479},
{"learn":[0.5212746325],"iteration":148,"passed_time":0.1808652942,"remaining_time":0.3046791197},
{"learn":[0.5208293642],"iteration":149,"passed_time":0.182256174,"remaining_time":0.30376029},
{"learn":[0.5205010799],"iteration":150,"passed_time":0.1834198235,"remaining_time":0.3024605037},
{"learn":[0.5203448059],"iteration":151,"passed_time":0.1846500089,"remaining_time":0.3012710672},
{"learn":[0.5198155709],"iteration":152,"passed_time":0.1858930266,"remaining_time":0.3001018141},
{"learn":[0.5194015525],"iteration":153,"passed_time":0.1871507513,"remaining_time":0.2989550962},
{"learn":[0.5188367951],"iteration":154,"passed_time":0.188381395,"remaining_time":0.2977641404},
{"learn":[0.5185317412],"iteration":155,"passed_time":0.1895550436,"remaining_time":0.2964835297},
{"learn":[0.5179313232],"iteration":156,"passed_time":0.1907341917,"remaining_time":0.2952127936},
{"learn":[0.5176953515],"iteration":157,"passed_time":0.1920478699,"remaining_time":0.2941492691},
{"learn":[0.5171904786],"iteration":158,"passed_time":0.1931469,"remaining_time":0.2927572509},
{"learn":[0.5168369273],"iteration":159,"passed_time":0.1943172156,"remaining_time":0.2914758234},
{"learn":[0.5164535715],"iteration":160,"passed_time":0.1955305274,"remaining_time":0.2902596028},
{"learn":[0.5160976687],"iteration":161,"passed_time":0.1967942099,"remaining_time":0.2891174196},
{"learn":[0.5156527214],"iteration":162,"passed_time":0.1980210623,"remaining_time":0.2879201949},
{"learn":[0.515427753],"iteration":163,"passed_time":0.199653338,"remaining_time":0.287306023},
{"learn":[0.5150544708],"iteration":164,"passed_time":0.2008306113,"remaining_time":0.2860314767},
{"learn":[0.5147885307],"iteration":165,"passed_time":0.2021357902,"remaining_time":0.2849384031},
{"learn":[0.5141864448],"iteration":166,"passed_time":0.2036695744,"remaining_time":0.2841617415},
{"learn":[0.5139060099],"iteration":167,"passed_time":0.2048465144,"remaining_time":0.2828832818},
{"learn":[0.5135697337],"iteration":168,"passed_time":0.2060233711,"remaining_time":0.2816059096},
{"learn":[0.5132710537],"iteration":169,"passed_time":0.2077745115,"remaining_time":0.281106692},
{"learn":[0.5129969299],"iteration":170,"passed_time":0.2093574165,"remaining_time":0.2803675343},
{"learn":[0.5125614905],"iteration":171,"passed_time":0.2106180992,"remaining_time":0.2791914339},
{"learn":[0.5122909134],"iteration":172,"passed_time":0.2118847398,"remaining_time":0.2780221731},
{"learn":[0.5119729757],"iteration":173,"passed_time":0.2130024766,"remaining_time":0.2766583892},
{"learn":[0.5117722936],"iteration":174,"passed_time":0.2143307369,"remaining_time":0.2755680903},
{"learn":[0.5114590705],"iteration":175,"passed_time":0.2157015768,"remaining_time":0.2745292796},
{"learn":[0.5109755662],"iteration":176,"passed_time":0.2168191053,"remaining_time":0.2731675733},
{"learn":[0.5106049455],"iteration":177,"passed_time":0.2180544152,"remaining_time":0.2719555066},
{"learn":[0.5102242905],"iteration":178,"passed_time":0.2195101645,"remaining_time":0.2710153428},
{"learn":[0.5099242874],"iteration":179,"passed_time":0.2205856133,"remaining_time":0.2696046384},
{"learn":[0.5094830123],"iteration":180,"passed_time":0.2216051919,"remaining_time":0.2681300388},
{"learn":[0.5092490987],"iteration":181,"passed_time":0.2228352939,"remaining_time":0.2669126048},
{"learn":[0.5089931715],"iteration":182,"passed_time":0.224069854,"remaining_time":0.2657003186},
{"learn":[0.5086701613],"iteration":183,"passed_time":0.2256853394,"remaining_time":0.2649349637},
{"learn":[0.5083139348],"iteration":184,"passed_time":0.2269262323,"remaining_time":0.2637250807},
{"learn":[0.5079242393],"iteration":185,"passed_time":0.228036303,"remaining_time":0.2623643487},
{"learn":[0.5076843932],"iteration":186,"passed_time":0.2293491063,"remaining_time":0.2612372173},
{"learn":[0.5073759808],"iteration":187,"passed_time":0.2305120892,"remaining_time":0.2599391644},
{"learn":[0.5068643837],"iteration":188,"passed_time":0.2318721384,"remaining_time":0.258862546},
{"learn":[0.5065478562],"iteration":189,"passed_time":0.2330670768,"remaining_time":0.2576004533},
{"learn":[0.5061983319],"iteration":190,"passed_time":0.2343156356,"remaining_time":0.2563977374},
{"learn":[0.5058834152],"iteration":191,"passed_time":0.2355371135,"remaining_time":0.2551652063},
{"learn":[0.5054365696],"iteration":192,"passed_time":0.2368217942,"remaining_time":0.2540005772},
{"learn":[0.5050107091],"iteration":193,"passed_time":0.2387307543,"remaining_time":0.2534976051},
{"learn":[0.5044806717],"iteration":194,"passed_time":0.2402343327,"remaining_time":0.2525540421},
{"learn":[0.5041632197],"iteration":195,"passed_time":0.2416952899,"remaining_time":0.2515604038},
{"learn":[0.5037698516],"iteration":196,"passed_time":0.2429475151,"remaining_time":0.2503469318},
{"learn":[0.5034958618],"iteration":197,"passed_time":0.2441529943,"remaining_time":0.249085378},
{"learn":[0.5029978216],"iteration":198,"passed_time":0.2452878546,"remaining_time":0.2477530591},
{"learn":[0.5027063245],"iteration":199,"passed_time":0.2463921759,"remaining_time":0.2463921759},
{"learn":[0.5022268148],"iteration":200,"passed_time":0.2476511921,"remaining_time":0.2451870011},
{"learn":[0.501923567],"iteration":201,"passed_time":0.2488247991,"remaining_time":0.2438975753},
{"learn":[0.5014417128],"iteration":202,"passed_time":0.2505181111,"remaining_time":0.2431136349},
{"learn":[0.501095868],"iteration":203,"passed_time":0.2517620454,"remaining_time":0.241889024},
{"learn":[0.5005960079],"iteration":204,"passed_time":0.2528875315,"remaining_time":0.2405515543},
{"learn":[0.5002996822],"iteration":205,"passed_time":0.2542814111,"remaining_time":0.2394689017},
{"learn":[0.5001439312],"iteration":206,"passed_time":0.2555731745,"remaining_time":0.2382880323},
{"learn":[0.4999644825],"iteration":207,"passed_time":0.2569325571,"remaining_time":0.2371685142},
{"learn":[0.4995589278],"iteration":208,"passed_time":0.2581579512,"remaining_time":0.2359242521},
{"learn":[0.4991469708],"iteration":209,"passed_time":0.2593023524,"remaining_time":0.2346068903},
{"learn":[0.4988191793],"iteration":210,"passed_time":0.260460919,"remaining_time":0.2333038563},
{"learn":[0.4984752124],"iteration":211,"passed_time":0.2615954043,"remaining_time":0.2319808302},
{"learn":[0.4980727545],"iteration":212,"passed_time":0.2627945507,"remaining_time":0.2307163427},
{"learn":[0.497562771],"iteration":213,"passed_time":0.2642566744,"remaining_time":0.2296810348},
{"learn":[0.4970697432],"iteration":214,"passed_time":0.2654303231,"remaining_time":0.2283935338},
{"learn":[0.4966197731],"iteration":215,"passed_time":0.2666757155,"remaining_time":0.2271682021},
{"learn":[0.4962499997],"iteration":216,"passed_time":0.2678633213,"remaining_time":0.2258939529},
{"learn":[0.4959108201],"iteration":217,"passed_time":0.2690075558,"remaining_time":0.2245842897},
{"learn":[0.4956732667],"iteration":218,"passed_time":0.2702143265,"remaining_time":0.2233278224},
{"learn":[0.4953769059],"iteration":219,"passed_time":0.2715375039,"remaining_time":0.2221670486},
{"learn":[0.49485242],"iteration":220,"passed_time":0.2728619728,"remaining_time":0.2210058513},
{"learn":[0.4944562142],"iteration":221,"passed_time":0.2741669434,"remaining_time":0.2198275492},
{"learn":[0.494163141],"iteration":222,"passed_time":0.2752978458,"remaining_time":0.2185099493},
{"learn":[0.4939008535],"iteration":223,"passed_time":0.2763625871,"remaining_time":0.2171420327},
{"learn":[0.4935234333],"iteration":224,"passed_time":0.2775339859,"remaining_time":0.2158597668},
{"learn":[0.4932015307],"iteration":225,"passed_time":0.2786867614,"remaining_time":0.2145641437},
{"learn":[0.4929576464],"iteration":226,"passed_time":0.2799479441,"remaining_time":0.2133523979},
{"learn":[0.4924004454],"iteration":227,"passed_time":0.2815105175,"remaining_time":0.2123675833},
{"learn":[0.4919106116],"iteration":228,"passed_time":0.2826976233,"remaining_time":0.2110973519},
{"learn":[0.4914756839],"iteration":229,"passed_time":0.2839519732,"remaining_time":0.2098775454},
{"learn":[0.4912245908],"iteration":230,"passed_time":0.2851282466,"remaining_time":0.208600319},
{"learn":[0.4907615596],"iteration":231,"passed_time":0.2863790136,"remaining_time":0.2073779064},
{"learn":[0.4904108237],"iteration":232,"passed_time":0.2875107908,"remaining_time":0.206069966},
{"learn":[0.4899211803],"iteration":233,"passed_time":0.2887692238,"remaining_time":0.204853381},
{"learn":[0.4895974698],"iteration":234,"passed_time":0.2900278234,"remaining_time":0.2036365569},
{"learn":[0.4892375212],"iteration":235,"passed_time":0.291160184,"remaining_time":0.2023316533},
{"learn":[0.4890149757],"iteration":236,"passed_time":0.2922868783,"remaining_time":0.2010243087},
{"learn":[0.4886164285],"iteration":237,"passed_time":0.2934730258,"remaining_time":0.1997589504},
{"learn":[0.4879617511],"iteration":238,"passed_time":0.2945937207,"remaining_time":0.1984501633},
{"learn":[0.4875738608],"iteration":239,"passed_time":0.2957465795,"remaining_time":0.1971643863},
{"learn":[0.4872260904],"iteration":240,"passed_time":0.2969879722,"remaining_time":0.1959381228},
{"learn":[0.4867509753],"iteration":241,"passed_time":0.2981774112,"remaining_time":0.1946778139},
{"learn":[0.4863972255],"iteration":242,"passed_time":0.2994270532,"remaining_time":0.193456985},
{"learn":[0.4859319028],"iteration":243,"passed_time":0.3008433892,"remaining_time":0.1923424947},
{"learn":[0.4854876974],"iteration":244,"passed_time":0.3019412111,"remaining_time":0.1910240315},
{"learn":[0.4849307892],"iteration":245,"passed_time":0.3031559811,"remaining_time":0.1897805736},
{"learn":[0.4843840943],"iteration":246,"passed_time":0.30432688,"remaining_time":0.1885101726},
{"learn":[0.4838081444],"iteration":247,"passed_time":0.3056552236,"remaining_time":0.1873370725},
{"learn":[0.4834858637],"iteration":248,"passed_time":0.3068409128,"remaining_time":0.1860762162},
{"learn":[0.4832061242],"iteration":249,"passed_time":0.3080292685,"remaining_time":0.1848175611},
{"learn":[0.4828412101],"iteration":250,"passed_time":0.3091901266,"remaining_time":0.1835431429},
{"learn":[0.4823905569],"iteration":251,"passed_time":0.3103176125,"remaining_time":0.1822500264},
{"learn":[0.4820166486],"iteration":252,"passed_time":0.3115414235,"remaining_time":0.1810141868},
{"learn":[0.4815331916],"iteration":253,"passed_time":0.3128387281,"remaining_time":0.1798206862},
{"learn":[0.4809845442],"iteration":254,"passed_time":0.3139607145,"remaining_time":0.1785266808},
{"learn":[0.480618536],"iteration":255,"passed_time":0.315391216,"remaining_time":0.177407559},
{"learn":[0.4803559887],"iteration":256,"passed_time":0.316648899,"remaining_time":0.1761898543},
{"learn":[0.4799618376],"iteration":257,"passed_time":0.3177673441,"remaining_time":0.1748952049},
{"learn":[0.4796700691],"iteration":258,"passed_time":0.3189362848,"remaining_time":0.173629406},
{"learn":[0.4792798849],"iteration":259,"passed_time":0.3201860935,"remaining_time":0.1724078965},
{"learn":[0.4787768558],"iteration":260,"passed_time":0.3213852815,"remaining_time":0.1711592112},
{"learn":[0.4782050591],"iteration":261,"passed_time":0.3227365815,"remaining_time":0.1699910238},
{"learn":[0.4777301853],"iteration":262,"passed_time":0.3238703169,"remaining_time":0.1687081118},
{"learn":[0.4770514581],"iteration":263,"passed_time":0.3251986605,"remaining_time":0.1675265827},
{"learn":[0.4766022215],"iteration":264,"passed_time":0.3264507607,"remaining_time":0.1663051045},
{"learn":[0.4760535431],"iteration":265,"passed_time":0.3275442496,"remaining_time":0.1650034941},
{"learn":[0.4756617702],"iteration":266,"passed_time":0.328689109,"remaining_time":0.1637290318},
{"learn":[0.4753032226],"iteration":267,"passed_time":0.3299742897,"remaining_time":0.1625246501},
{"learn":[0.4748885869],"iteration":268,"passed_time":0.331170103,"remaining_time":0.1612761468},
{"learn":[0.474447852],"iteration":269,"passed_time":0.3326016877,"remaining_time":0.1601415533},
{"learn":[0.4738856527],"iteration":270,"passed_time":0.3337427975,"remaining_time":0.1588664977},
{"learn":[0.4736374348],"iteration":271,"passed_time":0.3349074885,"remaining_time":0.157603524},
{"learn":[0.4733312295],"iteration":272,"passed_time":0.3362973685,"remaining_time":0.1564460286},
{"learn":[0.4728291161],"iteration":273,"passed_time":0.3374855575,"remaining_time":0.1551940885},
{"learn":[0.4723305485],"iteration":274,"passed_time":0.338826775,"remaining_time":0.1540121705},
{"learn":[0.4718440495],"iteration":275,"passed_time":0.340177825,"remaining_time":0.1528335156},
{"learn":[0.4714049048],"iteration":276,"passed_time":0.3413314337,"remaining_time":0.1515659435},
{"learn":[0.4710114273],"iteration":277,"passed_time":0.3424221311,"remaining_time":0.1502715827},
{"learn":[0.4706028892],"iteration":278,"passed_time":0.3436717315,"remaining_time":0.1490475968},
{"learn":[0.4700793229],"iteration":279,"passed_time":0.3447537631,"remaining_time":0.1477516127},
{"learn":[0.469676274],"iteration":280,"passed_time":0.3459449935,"remaining_time":0.1465033958},
{"learn":[0.4691934172],"iteration":281,"passed_time":0.3471377238,"remaining_time":0.1452562107},
{"learn":[0.4687050429],"iteration":282,"passed_time":0.3483782,"remaining_time":0.1440291498},
{"learn":[0.4682033935],"iteration":283,"passed_time":0.3496306335,"remaining_time":0.1428068785},
{"learn":[0.4677031598],"iteration":284,"passed_time":0.3509394371,"remaining_time":0.1416071413},
{"learn":[0.467387184],"iteration":285,"passed_time":0.3522354918,"remaining_time":0.1404015597},
{"learn":[0.4669601662],"iteration":286,"passed_time":0.3533980997,"remaining_time":0.1391428058},
{"learn":[0.4664168661],"iteration":287,"passed_time":0.354780147,"remaining_time":0.1379700572},
{"learn":[0.4658237354],"iteration":288,"passed_time":0.3560194983,"remaining_time":0.136741053},
{"learn":[0.4654167454],"iteration":289,"passed_time":0.3571926053,"remaining_time":0.1354868503},
{"learn":[0.4650283038],"iteration":290,"passed_time":0.3584788275,"remaining_time":0.1342755746},
{"learn":[0.4646244645],"iteration":291,"passed_time":0.3595906898,"remaining_time":0.1329992962},
{"learn":[0.4641881914],"iteration":292,"passed_time":0.3606848453,"remaining_time":0.1317176739},
{"learn":[0.4637772404],"iteration":293,"passed_time":0.3617312966,"remaining_time":0.1304201273},
{"learn":[0.4633374668],"iteration":294,"passed_time":0.3630528075,"remaining_time":0.1292221857},
{"learn":[0.4628798885],"iteration":295,"passed_time":0.3641511293,"remaining_time":0.1279449914},
{"learn":[0.4623944189],"iteration":296,"passed_time":0.3653402765,"remaining_time":0.1267004999},
{"learn":[0.4619054502],"iteration":297,"passed_time":0.3666689118,"remaining_time":0.1255041242},
{"learn":[0.4614449683],"iteration":298,"passed_time":0.3678275617,"remaining_time":0.1242494439},
{"learn":[0.4609578968],"iteration":299,"passed_time":0.3689949192,"remaining_time":0.1229983064},
{"learn":[0.4604549737],"iteration":300,"passed_time":0.3701185721,"remaining_time":0.121733351},
{"learn":[0.459961209],"iteration":301,"passed_time":0.3713850044,"remaining_time":0.1205156637},
{"learn":[0.4594801073],"iteration":302,"passed_time":0.3724820763,"remaining_time":0.119243437},
{"learn":[0.4591771492],"iteration":303,"passed_time":0.3736882638,"remaining_time":0.1180068201},
{"learn":[0.4586729714],"iteration":304,"passed_time":0.3748263322,"remaining_time":0.1167491854},
{"learn":[0.4582851548],"iteration":305,"passed_time":0.3760610172,"remaining_time":0.1155220118},
{"learn":[0.4578842941],"iteration":306,"passed_time":0.3773082428,"remaining_time":0.1142985882},
{"learn":[0.4573843115],"iteration":307,"passed_time":0.3784807248,"remaining_time":0.113052684},
{"learn":[0.456941843],"iteration":308,"passed_time":0.3795933787,"remaining_time":0.1117896358},
{"learn":[0.4565167863],"iteration":309,"passed_time":0.3809425539,"remaining_time":0.1105962253},
{"learn":[0.4561124922],"iteration":310,"passed_time":0.3821467832,"remaining_time":0.1093603335},
{"learn":[0.4556217722],"iteration":311,"passed_time":0.3833515958,"remaining_time":0.1081248091},
{"learn":[0.4550519336],"iteration":312,"passed_time":0.3845714488,"remaining_time":0.1068936615},
{"learn":[0.454793734],"iteration":313,"passed_time":0.3863761262,"remaining_time":0.1058227607},
{"learn":[0.4545010101],"iteration":314,"passed_time":0.3875566076,"remaining_time":0.1045787671},
{"learn":[0.4541481809],"iteration":315,"passed_time":0.3888527873,"remaining_time":0.1033659308},
{"learn":[0.4535888233],"iteration":316,"passed_time":0.3899341939,"remaining_time":0.1020963347},
{"learn":[0.4530752517],"iteration":317,"passed_time":0.3910232248,"remaining_time":0.1008298882},
{"learn":[0.4527531426],"iteration":318,"passed_time":0.3921299209,"remaining_time":0.09956903947},
{"learn":[0.4522488701],"iteration":319,"passed_time":0.3932660727,"remaining_time":0.09831651819},
{"learn":[0.4518806544],"iteration":320,"passed_time":0.3945627941,"remaining_time":0.09710423904},
{"learn":[0.4516159262],"iteration":321,"passed_time":0.3957803556,"remaining_time":0.09587226004},
{"learn":[0.4512634181],"iteration":322,"passed_time":0.3969685446,"remaining_time":0.09463336822},
{"learn":[0.4508422641],"iteration":323,"passed_time":0.3981239031,"remaining_time":0.09338708839},
{"learn":[0.4505228861],"iteration":324,"passed_time":0.3994728283,"remaining_time":0.0921860373},
{"learn":[0.4501796783],"iteration":325,"passed_time":0.4007653,"remaining_time":0.09097126441},
{"learn":[0.4497765907],"iteration":326,"passed_time":0.402054147,"remaining_time":0.08975520713},
{"learn":[0.4493738628],"iteration":327,"passed_time":0.4033347031,"remaining_time":0.08853688604},
{"learn":[0.4489781594],"iteration":328,"passed_time":0.4047338322,"remaining_time":0.08734377534},
{"learn":[0.4486560689],"iteration":329,"passed_time":0.4058670676,"remaining_time":0.08609301435},
{"learn":[0.4481976578],"iteration":330,"passed_time":0.4070949199,"remaining_time":0.08486268723},
{"learn":[0.447787918],"iteration":331,"passed_time":0.4083611855,"remaining_time":0.08364024282},
{"learn":[0.4473098598],"iteration":332,"passed_time":0.4095927875,"remaining_time":0.08241056085},
{"learn":[0.4469544351],"iteration":333,"passed_time":0.4106972754,"remaining_time":0.08115574904},
{"learn":[0.446430609],"iteration":334,"passed_time":0.4120378263,"remaining_time":0.07994763794},
{"learn":[0.446047912],"iteration":335,"passed_time":0.4131982261,"remaining_time":0.07870442401},
{"learn":[0.4454811366],"iteration":336,"passed_time":0.4144939475,"remaining_time":0.07748699909},
{"learn":[0.4452232245],"iteration":337,"passed_time":0.4157206332,"remaining_time":0.07625644751},
{"learn":[0.444923361],"iteration":338,"passed_time":0.416930862,"remaining_time":0.07502295747},
{"learn":[0.4444514558],"iteration":339,"passed_time":0.4182249585,"remaining_time":0.07380440445},
{"learn":[0.4441900566],"iteration":340,"passed_time":0.4193853167,"remaining_time":0.07256226886},
{"learn":[0.4438878866],"iteration":341,"passed_time":0.4206175019,"remaining_time":0.07133279272},
{"learn":[0.4434295006],"iteration":342,"passed_time":0.4217201983,"remaining_time":0.07008178223},
{"learn":[0.4430709361],"iteration":343,"passed_time":0.4229941299,"remaining_time":0.06885950952},
{"learn":[0.4426573118],"iteration":344,"passed_time":0.4241371979,"remaining_time":0.06761607502},
{"learn":[0.4423359093],"iteration":345,"passed_time":0.4252574761,"remaining_time":0.0663696639},
{"learn":[0.441979304],"iteration":346,"passed_time":0.4265064932,"remaining_time":0.06514364306},
{"learn":[0.4416194769],"iteration":347,"passed_time":0.4277343872,"remaining_time":0.06391433371},
{"learn":[0.4412896422],"iteration":348,"passed_time":0.4290678136,"remaining_time":0.06270045414},
{"learn":[0.4411382105],"iteration":349,"passed_time":0.4302295466,"remaining_time":0.06146136381},
{"learn":[0.4407376247],"iteration":350,"passed_time":0.4316450494,"remaining_time":0.0602581408},
{"learn":[0.4403659302],"iteration":351,"passed_time":0.4328088655,"remaining_time":0.05901939075},
{"learn":[0.439984571],"iteration":352,"passed_time":0.4338897721,"remaining_time":0.05777002632},
{"learn":[0.4394723801],"iteration":353,"passed_time":0.4351864935,"remaining_time":0.05654965734},
{"learn":[0.4389852182],"iteration":354,"passed_time":0.4364485511,"remaining_time":0.05532446423},
{"learn":[0.4387340892],"iteration":355,"passed_time":0.4376827362,"remaining_time":0.05409561908},
{"learn":[0.4382314701],"iteration":356,"passed_time":0.4388184714,"remaining_time":0.05285488591},
{"learn":[0.4376883621],"iteration":357,"passed_time":0.4400650721,"remaining_time":0.05162774589},
{"learn":[0.4373929346],"iteration":358,"passed_time":0.4412380541,"remaining_time":0.05039208974},
{"learn":[0.4370655318],"iteration":359,"passed_time":0.4423204189,"remaining_time":0.04914671322},
{"learn":[0.4365066291],"iteration":360,"passed_time":0.4433997424,"remaining_time":0.04790191123},
{"learn":[0.4361778708],"iteration":361,"passed_time":0.4450344762,"remaining_time":0.04671632623},
{"learn":[0.4357763602],"iteration":362,"passed_time":0.4462108329,"remaining_time":0.04548154495},
{"learn":[0.4352877188],"iteration":363,"passed_time":0.4473842315,"remaining_time":0.04424679213},
{"learn":[0.43481455],"iteration":364,"passed_time":0.4485290493,"remaining_time":0.04300963487},
{"learn":[0.4343625476],"iteration":365,"passed_time":0.4497090724,"remaining_time":0.04177625263},
{"learn":[0.4339723563],"iteration":366,"passed_time":0.4508588481,"remaining_time":0.04054044138},
{"learn":[0.4335469877],"iteration":367,"passed_time":0.4521475701,"remaining_time":0.03931718001},
{"learn":[0.4331070549],"iteration":368,"passed_time":0.4532739311,"remaining_time":0.03807992375},
{"learn":[0.4327523036],"iteration":369,"passed_time":0.4546067744,"remaining_time":0.03686000873},
{"learn":[0.4323414106],"iteration":370,"passed_time":0.4558993294,"remaining_time":0.03563633572},
{"learn":[0.4320017395],"iteration":371,"passed_time":0.4570714365,"remaining_time":0.0344032264},
{"learn":[0.4315762536],"iteration":372,"passed_time":0.4583170372,"remaining_time":0.03317576409},
{"learn":[0.431132177],"iteration":373,"passed_time":0.4594896859,"remaining_time":0.03194313325},
{"learn":[0.4306866467],"iteration":374,"passed_time":0.4606854576,"remaining_time":0.03071236384},
{"learn":[0.4304181358],"iteration":375,"passed_time":0.4620662967,"remaining_time":0.02949359341},
{"learn":[0.4300870322],"iteration":376,"passed_time":0.4632944823,"remaining_time":0.02826465011},
{"learn":[0.4296900711],"iteration":377,"passed_time":0.4644610065,"remaining_time":0.02703212207},
{"learn":[0.4293314411],"iteration":378,"passed_time":0.4657151065,"remaining_time":0.02580479482},
{"learn":[0.429059091],"iteration":379,"passed_time":0.4669421672,"remaining_time":0.02457590354},
{"learn":[0.4285983012],"iteration":380,"passed_time":0.4681155242,"remaining_time":0.02334434373},
{"learn":[0.4283727962],"iteration":381,"passed_time":0.4695753981,"remaining_time":0.02212658944},
{"learn":[0.4278578621],"iteration":382,"passed_time":0.4713925745,"remaining_time":0.0209234302},
{"learn":[0.4274518577],"iteration":383,"passed_time":0.4728757797,"remaining_time":0.01970315749},
{"learn":[0.4271134527],"iteration":384,"passed_time":0.4741075066,"remaining_time":0.01847172104},
{"learn":[0.4267264326],"iteration":385,"passed_time":0.4754834711,"remaining_time":0.0172455145},
{"learn":[0.4263352159],"iteration":386,"passed_time":0.4766552449,"remaining_time":0.01601167489},
{"learn":[0.425929183],"iteration":387,"passed_time":0.4781560319,"remaining_time":0.01478833088},
{"learn":[0.4255333717],"iteration":388,"passed_time":0.4793870922,"remaining_time":0.0135559332},
{"learn":[0.4252368169],"iteration":389,"passed_time":0.4805791143,"remaining_time":0.01232254139},
{"learn":[0.4249534221],"iteration":390,"passed_time":0.4818870013,"remaining_time":0.01109202816},
{"learn":[0.4247348721],"iteration":391,"passed_time":0.4830629831,"remaining_time":0.009858428226},
{"learn":[0.4243269567],"iteration":392,"passed_time":0.4841340989,"remaining_time":0.00862325367},
{"learn":[0.4239126889],"iteration":393,"passed_time":0.4853178716,"remaining_time":0.007390627487},
{"learn":[0.4235332567],"iteration":394,"passed_time":0.4865934698,"remaining_time":0.00615941101},
{"learn":[0.4230614111],"iteration":395,"passed_time":0.4879589768,"remaining_time":0.004928878554},
{"learn":[0.4228122956],"iteration":396,"passed_time":0.4892045776,"remaining_time":0.003696760032},
{"learn":[0.4224960831],"iteration":397,"passed_time":0.4904377627,"remaining_time":0.002464511371},
{"learn":[0.4220883254],"iteration":398,"passed_time":0.4917070698,"remaining_time":0.001232348546},
{"learn":[0.4216283273],"iteration":399,"passed_time":0.4928180571,"remaining_time":0}
]}